example.py
nurmuhammadown_package2-0.0.0.3.dist-info/METADATA
nurmuhammadown_package2-0.0.0.3.dist-info/WHEEL
nurmuhammadown_package2-0.0.0.3.dist-info/top_level.txt
nurmuhammadown_package2-0.0.0.3.dist-info/RECORD
